LICENSE.txt
MANIFEST.in
README.rst
VERSION
requirements.txt
setup.py
pyvoltha_min/__init__.py
pyvoltha_min.egg-info/PKG-INFO
pyvoltha_min.egg-info/SOURCES.txt
pyvoltha_min.egg-info/dependency_links.txt
pyvoltha_min.egg-info/requires.txt
pyvoltha_min.egg-info/top_level.txt
pyvoltha_min/adapters/__init__.py
pyvoltha_min/adapters/iadapter.py
pyvoltha_min/adapters/interface.py
pyvoltha_min/adapters/log_controller.py
pyvoltha_min/adapters/log_features.py
pyvoltha_min/adapters/common/__init__.py
pyvoltha_min/adapters/common/pon_resource_manager/__init__.py
pyvoltha_min/adapters/common/pon_resource_manager/resource_kv_store.py
pyvoltha_min/adapters/common/pon_resource_manager/resource_manager.py
pyvoltha_min/adapters/extensions/__init__.py
pyvoltha_min/adapters/extensions/events/__init__.py
pyvoltha_min/adapters/extensions/events/adapter_events.py
pyvoltha_min/adapters/extensions/events/device_events/__init__.py
pyvoltha_min/adapters/extensions/events/device_events/olt/__init__.py
pyvoltha_min/adapters/extensions/events/device_events/olt/olt_indication_event.py
pyvoltha_min/adapters/extensions/events/device_events/olt/olt_los_event.py
pyvoltha_min/adapters/extensions/events/device_events/olt/olt_pon_interface_event.py
pyvoltha_min/adapters/extensions/events/device_events/onu/__init__.py
pyvoltha_min/adapters/extensions/events/device_events/onu/onu_activation_fail_event.py
pyvoltha_min/adapters/extensions/events/device_events/onu/onu_active_event.py
pyvoltha_min/adapters/extensions/events/device_events/onu/onu_deleted_event.py
pyvoltha_min/adapters/extensions/events/device_events/onu/onu_disabled_event.py
pyvoltha_min/adapters/extensions/events/device_events/onu/onu_discovery_event.py
pyvoltha_min/adapters/extensions/events/device_events/onu/onu_dying_gasp_event.py
pyvoltha_min/adapters/extensions/events/device_events/onu/onu_ethernet_uni_event.py
pyvoltha_min/adapters/extensions/events/device_events/onu/onu_lob_event.py
pyvoltha_min/adapters/extensions/events/device_events/onu/onu_lopc_mic_error_event.py
pyvoltha_min/adapters/extensions/events/device_events/onu/onu_lopc_miss_event.py
