Metadata-Version: 2.1
Name: pyvoltha-min
Version: 2.8.0
Summary: VOLTHA Python OLT Device Adapter support libraries
Home-page: https://github.com/cboling/pyvoltha-min
Author: Chip Boling
Author-email: chip@bcsw.net
Classifier: Development Status :: 5 - Production/Stable
Classifier: Intended Audience :: Developers
Classifier: Topic :: Software Development :: Libraries
Classifier: License :: OSI Approved :: Apache Software License
Classifier: Programming Language :: Python :: 3.6
Classifier: Programming Language :: Python :: 3.7
Classifier: Programming Language :: Python :: 3.8
Classifier: Programming Language :: Python :: 3.9
License-File: LICENSE.txt
